prefs_n_perms/__init__.py
prefs_n_perms/apps.py
prefs_n_perms/base.py
prefs_n_perms/client.py
prefs_n_perms/config.py
prefs_n_perms/decorators.py
prefs_n_perms/exceptions.py
prefs_n_perms/managers.py
prefs_n_perms/permissions.py
prefs_n_perms/pool.py
prefs_n_perms/preferences.py
prefs_n_perms/registries.py
prefs_n_perms/sections.py
prefs_n_perms/settings.py
prefs_n_perms/utils.py
prefs_n_perms/management/__init__.py
prefs_n_perms/management/commands/__init__.py
prefs_n_perms/management/commands/update_prefs_n_perms.py
prefs_n_perms-0.2.5.dist-info/DESCRIPTION.rst
prefs_n_perms-0.2.5.dist-info/METADATA
prefs_n_perms-0.2.5.dist-info/RECORD
prefs_n_perms-0.2.5.dist-info/WHEEL
prefs_n_perms-0.2.5.dist-info/metadata.json
prefs_n_perms-0.2.5.dist-info/top_level.txt
prefs_n_perms-0.2.5.dist-info/zip-safe
test/__init__.py
test/settings.py
test/tests.py
test/urls.py
test/test_app/__init__.py
test/test_app/models.py
test/test_app/prefs.py
test/test_app/views.py
