Metadata-Version: 2.0
Name: prefs-n-perms
Version: 0.2.5
Summary: Manage preferences and permissions with hierarchy structure
Home-page: https://github.com/revpoint/prefs-n-perms
Author: RevPoint Media LLC
Author-email: jangl@revpointmedia.com
License: UNKNOWN
Platform: UNKNOWN
Requires-Dist: hiredis
Requires-Dist: redis
Requires-Dist: redish
